datasets/__init__.py
datasets/base.py
datasets/data/TS_ECG0606_1.csv
datasets/data/TS_ECG108_1.csv
datasets/data/TS_ECG108_2.csv
datasets/data/TS_chfdb_1.csv
datasets/data/hbk.csv
datasets/data/isolet.csv
datasets/data/shuttle.csv
zw_outliersdetec/FastVOA.py
zw_outliersdetec/HOTSAX.py
zw_outliersdetec/IntervalSets.py
zw_outliersdetec/PAPR.py
zw_outliersdetec/RDOS.py
zw_outliersdetec/__dimension_reduction.py
zw_outliersdetec/__init__.py
zw_outliersdetec/__paa.py
zw_outliersdetec/__sax_via_window.py
zw_outliersdetec/dimension_reduction.py
zw_outliersdetec/iForest.py
zw_outliersdetec/paa.py
zw_outliersdetec/sax_via_window.py
zw_outliersdetec/setup.py
zw_outliersdetec/datasets/__init__.py
zw_outliersdetec/datasets/base.py
zw_outliersdetec-0.0.1.dist-info/LICENSE
zw_outliersdetec-0.0.1.dist-info/METADATA
zw_outliersdetec-0.0.1.dist-info/WHEEL
zw_outliersdetec-0.0.1.dist-info/top_level.txt
zw_outliersdetec-0.0.1.dist-info/RECORD
