Metadata-Version: 2.1
Name: zw-outliersdetec
Version: 0.0.1
Summary: A small outliers-detection package
Home-page: https://github.com/vidiewei
Author: Zuo Wei
Author-email: zw@my.swjtu.edu.cn
License: UNKNOWN
Platform: UNKNOWN
Classifier: Programming Language :: Python :: 3
Classifier: License :: OSI Approved :: MIT License
Classifier: Operating System :: OS Independent
